{
  "type": "FeatureCollection",
  "name": "tern-points-down",
  "crs": {
    "type": "name",
    "properties": {
      "name": "urn:ogc:def:crs:OGC:1.3:CRS84"
    }
  },
  "features": [
    {
      "type": "Feature",
      "properties": {
        "timestamp": "2017-09-01 13:01:00",
        "long": -113.1022793,
        "lat": 23.62378974
      },
      "geometry": {
        "type": "Point",
        "coordinates": [
          -113.1022793,
          23.62378974
        ]
      }
    }
  ]
}