{
  "type": "FeatureCollection",
  "name": "tern-points-down",
  "crs": {
    "type": "name",
    "properties": {
      "name": "urn:ogc:def:crs:OGC:1.3:CRS84"
    }
  },
  "features": [
    {
      "type": "Feature",
      "properties": {
        "timestamp": "2017-09-17 23:41:00",
        "long": -82.55277877,
        "lat": -21.01130904
      },
      "geometry": {
        "type": "Point",
        "coordinates": [
          -82.55277877,
          -21.01130904
        ]
      }
    }
  ]
}