{"type": "FeatureCollection", "name": "tern-points-down", "crs": {"type": "name", "properties": {"name": "urn:ogc:def:crs:OGC:1.3:CRS84"}}, "features": [{"type": "Feature", "properties": {"timestamp": "2017-08-22 05:11:00", "lat": 53.35328538, "long": -145.5064424}, "geometry": {"type": "Point", "coordinates": [-145.5064424, 53.35328538]}}]}